{
  "input": {
    "type": "fieldset",
    "Beschriftung": "Eingangstabelle auswählen",
    "repeat": false,
    "fields": {
      "input_table": {
        "type": "select",
        "Beschriftung": "Tabelle auswählen",
        "bind": "TABLES",
        "empty": "",
        "required": true
      },
      "remove_input_table_after_processing": {
        "type": "hidden",
        "val": "false"
      },
      "is_word": {
        "type": "hidden",
        "val": "false"
      },
      "apply_to_all_columns": {
        "type": "checkbox",
        "Beschriftung": "Auf alle Spalten anwenden",
        "show_if": "table_type=='header_only' || table_type=='matrix'",
        "val": "true",
        "isOn": "true",
        "isOff": "false"
      },
      "columns_to_apply": {
        "type": "select",
        "Beschriftung": "Zu verwendende Spalten",
        "show_if": "apply_to_all_columns=='false' && (table_type=='header_only' || table_type=='matrix')",
        "table": "input_table",
        "bind": "COLUMNS",
        "multiple": true,
        "required": true,
        "breakLine": true
      }
    }
  }
}