{
  "options": {
    "type": "fieldset",
    "ラベル": "並び替えオプション",
    "repeat": false,
    "fields": {
      "sort": {
        "type": "fieldset",
        "ラベル": "並び替える列の選択",
        "repeat": true,
        "fields": {
          "column": {
            "type": "select",
            "ラベル": "列",
            "table": "input_table",
            "bind": "COLUMNS",
            "required": true
          },
          "order": {
            "type": "select",
            "ラベル": "注文",
            "options": {
              "asc": {
                "ラベル": "昇順"
              },
              "desc": {
                "ラベル": "降順"
              }
            },
            "val": "asc"
          },
          "delete": {
            "type": "button",
            "ラベル": "削除",
            "function": "DELETE_ROW"
          }
        }
      }
    }
  }
}